DriverPower-1.0.2.dist-info/METADATA
DriverPower-1.0.2.dist-info/RECORD
DriverPower-1.0.2.dist-info/WHEEL
DriverPower-1.0.2.dist-info/entry_points.txt
DriverPower-1.0.2.dist-info/top_level.txt
driverpower/__init__.py
driverpower/dataIO.py
driverpower/infer.py
driverpower/interface.py
driverpower/model.py
driverpower/xgb_param.pkl
driverpower/xgb_param_default.py
